BlurWindow/blurWindow.py
BlurWindow-1.2.1.dist-info/METADATA
BlurWindow-1.2.1.dist-info/WHEEL
BlurWindow-1.2.1.dist-info/top_level.txt
BlurWindow-1.2.1.dist-info/RECORD
