Metadata-Version: 2.1
Name: BlurWindow
Version: 1.2.1
Summary: Blur PySide, Tkinter, etc windows.
Home-page: https://github.com/Peticali/PythonBlurBehind
Author: Peticali
Author-email: pedropalmeira68@gmail.com
License: MIT
Platform: UNKNOWN
